q1x/__init__.py
q1x/base/__init__.py
q1x/base/app.py
q1x/base/base.py
q1x/base/cache.py
q1x/base/config.py
q1x/base/device.py
q1x/base/devp.py
q1x/base/exchange.py
q1x/base/file.py
q1x/base/logger.py
q1x/base/market.py
q1x/base/network.py
q1x/base/numerics.py
q1x/base/pattern.py
q1x/base/timestamp.py
q1x/base/version.py
q1x/core/__init__.py
q1x/core/factors.py
q1x/core/formula.py
q1x/core/option.py
q1x/core/option_test.py
q1x/core/power.py
q1x/core/test-snapshot-premarket.py
q1x/core/vix_option.py
q1x/core/vix_stock.py
q1x/core/w1.py
q1x/core/w2.py
q1x/core/waves.py
q1x/core/waves_test.py
quant1x_base-0.6.29.dist-info/licenses/LICENSE
quant1x_base-0.6.29.dist-info/METADATA
quant1x_base-0.6.29.dist-info/WHEEL
quant1x_base-0.6.29.dist-info/top_level.txt
quant1x_base-0.6.29.dist-info/RECORD
