Metadata-Version: 2.4
Name: quant1x-base
Version: 0.6.29
Summary: Quant1X量化系统python基础库
Home-page: https://gitee.com/quant1x/q1x-base
Author: WangFeng
Author-email: wangfengxy@sina.cn
License: MIT license
Keywords: quant1x base
Classifier: Development Status :: 2 - Pre-Alpha
Classifier: Intended Audience :: Developers
Classifier: License :: OSI Approved :: MIT License
Classifier: Natural Language :: English
Classifier: Programming Language :: Python :: 3
Classifier: Programming Language :: Python :: 3.8
Classifier: Programming Language :: Python :: 3.9
Classifier: Programming Language :: Python :: 3.10
Classifier: Programming Language :: Python :: 3.11
Classifier: Programming Language :: Python :: 3.12
License-File: LICENSE
Requires-Dist: setuptools~=78.0.0
Requires-Dist: twine~=6.1.0
Requires-Dist: wheel~=0.45.1
Requires-Dist: requests-toolbelt~=1.0.0
Requires-Dist: loguru~=0.7.3
Requires-Dist: icecream~=2.1.4
Requires-Dist: PyYAML~=6.0.2
Requires-Dist: numpy~=2.3.0
Requires-Dist: pandas~=2.3.0
Requires-Dist: gitpython~=3.1.44
Requires-Dist: python-dateutil~=2.9.0.post0
Requires-Dist: matplotlib~=3.10.5
Requires-Dist: akshare~=1.17.26
Requires-Dist: findpeaks~=2.7.4
Dynamic: author
Dynamic: author-email
Dynamic: classifier
Dynamic: description
Dynamic: description-content-type
Dynamic: home-page
Dynamic: keywords
Dynamic: license
Dynamic: license-file
Dynamic: requires-dist
Dynamic: summary
